strava/__init__.py
strava/cli.py
strava/decorators.py
strava/emoji.py
strava/formatters.py
strava/settings.py
strava/api/__init__.py
strava/api/_helpers.py
strava/api/activity.py
strava/api/athlete.py
strava/api/oauth2.py
strava/api/upload.py
strava/api/templates/fail.html
strava/api/templates/ok.html
strava/commands/__init__.py
strava/commands/activities.py
strava/commands/activity.py
strava/commands/config.py
strava/commands/login.py
strava/commands/logout.py
strava/commands/profile.py
strava/commands/stats.py
strava/commands/upload.py
strava/config/__init__.py
strava/config/config_store.py
strava/config/creds_store.py
strava/config/local_store.py
strava_cli-0.7.0.dist-info/LICENSE
strava_cli-0.7.0.dist-info/METADATA
strava_cli-0.7.0.dist-info/WHEEL
strava_cli-0.7.0.dist-info/entry_points.txt
strava_cli-0.7.0.dist-info/top_level.txt
strava_cli-0.7.0.dist-info/RECORD
