Metadata-Version: 2.1
Name: strava-cli
Version: 0.7.0
Summary: Strava Command-Line Tools
Home-page: https://github.com/bwilczynski/strava-cli
Author: Bartlomiej Wilczynski
Author-email: me@bwilczynski.com
Requires-Python: >=3.0
License-File: LICENSE
Requires-Dist: click
Requires-Dist: requests
Requires-Dist: requests-oauthlib
Requires-Dist: tabulate
Requires-Dist: dateparser
